HRProfiler/__init__.py
HRProfiler/version.py
HRProfiler/scripts/HRProfiler.py
HRProfiler/scripts/features.py
HRProfiler/scripts/plotting.py
HRProfiler/scripts/predict.py
HRProfiler/scripts/Models/WES/HRProfiler_WES_BREAST.sav
HRProfiler/scripts/Models/WES/HRProfiler_WES_OVARIAN.sav
HRProfiler/scripts/Models/WGS/HRProfiler_WGS_BREAST.sav
hrprofiler-0.0.2.dist-info/METADATA
hrprofiler-0.0.2.dist-info/WHEEL
hrprofiler-0.0.2.dist-info/top_level.txt
hrprofiler-0.0.2.dist-info/RECORD
