Metadata-Version: 2.4
Name: HRProfiler
Version: 0.0.2
Summary: HRD Prediction from WGS and WES samples
Home-page: https://github.com/AlexandrovLab/HRProfiler.git
Author: Ammal Abbasi
Author-email: amabbasi@ucsd.edu
License: UCSD
Requires-Python: >=3.9
Requires-Dist: sigProfilerPlotting>=1.4.1
Requires-Dist: SigProfilerMatrixGenerator>=1.3.5
Requires-Dist: joblib>=0.16.0
Requires-Dist: scikit-plot==0.3.7
Requires-Dist: scikit-learn>=1.1.3
Requires-Dist: seaborn
Requires-Dist: numpy>=2.0.0
Requires-Dist: pandas>=2.0.0
Requires-Dist: matplotlib>=3.4.3
Dynamic: author
Dynamic: author-email
Dynamic: description
Dynamic: description-content-type
Dynamic: home-page
Dynamic: license
Dynamic: requires-dist
Dynamic: requires-python
Dynamic: summary
